{
  "generated_at": "2026-03-14T04:55:42.323250",
  "date": "20260319",
  "campuses": [
    {
      "name": "SEDE LEONARDO",
      "id": "MIA01",
      "buildings": [
        {
          "name": "Edificio 2",
          "classrooms": [
            {
              "name": "2.0.1",
              "id": 32,
              "occupancy": [
                {
                  "inizio": "08:15",
                  "fine": "10:15"
                },
                {
                  "inizio": "10:15",
                  "fine": "12:15"
                },
                {
                  "inizio": "12:15",
                  "fine": "14:15"
                },
                {
                  "inizio": "14:15",
                  "fine": "17:15"
                }
              ]
            },
            {
              "name": "2.0.2",
              "id": 33,
              "occupancy": [
                {
                  "inizio": "08:15",
                  "fine": "16:15"
                },
                {
                  "inizio": "17:15",
                  "fine": "19:45"
                }
              ]
            },
            {
              "name": "2.1.1",
              "id": 34,
              "occupancy": [
                {
                  "inizio": "10:15",
                  "fine": "13:15"
                },
                {
                  "inizio": "13:15",
                  "fine": "15:15"
                },
                {
                  "inizio": "15:15",
                  "fine": "17:15"
                },
                {
                  "inizio": "17:45",
                  "fine": "19:30"
                }
              ]
            },
            {
              "name": "2.1.2",
              "id": 35,
              "occupancy": [
                {
                  "inizio": "08:15",
                  "fine": "10:15"
                },
                {
                  "inizio": "10:15",
                  "fine": "12:15"
                },
                {
                  "inizio": "13:15",
                  "fine": "15:15"
                },
                {
                  "inizio": "15:15",
                  "fine": "17:15"
                },
                {
                  "inizio": "17:15",
                  "fine": "19:15"
                }
              ]
            },
            {
              "name": "2.1.3",
              "id": 36,
              "occupancy": [
                {
                  "inizio": "08:15",
                  "fine": "11:15"
                },
                {
                  "inizio": "11:15",
                  "fine": "14:15"
                },
                {
                  "inizio": "14:15",
                  "fine": "16:15"
                },
                {
                  "inizio": "16:15",
                  "fine": "18:15"
                },
                {
                  "inizio": "18:15",
                  "fine": "19:15"
                }
              ]
            },
            {
              "name": "2.1.4",
              "id": 39,
              "occupancy": [
                {
                  "inizio": "10:15",
                  "fine": "12:15"
                },
                {
                  "inizio": "12:15",
                  "fine": "13:15"
                },
                {
                  "inizio": "13:15",
                  "fine": "16:15"
                },
                {
                  "inizio": "16:15",
                  "fine": "18:15"
                }
              ]
            },
            {
              "name": "2.1.5",
              "id": 38,
              "occupancy": [
                {
                  "inizio": "08:15",
                  "fine": "10:15"
                },
                {
                  "inizio": "10:15",
                  "fine": "12:15"
                },
                {
                  "inizio": "13:15",
                  "fine": "15:15"
                },
                {
                  "inizio": "15:15",
                  "fine": "17:15"
                }
              ]
            },
            {
              "name": "2.2.1",
              "id": 1303,
              "occupancy": [
                {
                  "inizio": "09:15",
                  "fine": "18:15"
                }
              ]
            },
            {
              "name": "2.2.2",
              "id": 41,
              "occupancy": [
                {
                  "inizio": "15:15",
                  "fine": "17:15"
                }
              ]
            },
            {
              "name": "2.2.3",
              "id": 961,
              "occupancy": [
                {
                  "inizio": "09:15",
                  "fine": "18:15"
                }
              ]
            },
            {
              "name": "2.2.4",
              "id": 4726,
              "occupancy": [
                {
                  "inizio": "09:15",
                  "fine": "13:15"
                },
                {
                  "inizio": "14:15",
                  "fine": "16:15"
                }
              ]
            }
          ]
        },
        {
          "name": "Edificio 3",
          "classrooms": [
            {
              "name": "3.0.1",
              "id": 42,
              "occupancy": [
                {
                  "inizio": "09:15",
                  "fine": "13:15"
                },
                {
                  "inizio": "14:15",
                  "fine": "18:15"
                }
              ]
            },
            {
              "name": "3.0.2",
              "id": 58,
              "occupancy": [
                {
                  "inizio": "08:15",
                  "fine": "10:15"
                },
                {
                  "inizio": "10:15",
                  "fine": "12:15"
                },
                {
                  "inizio": "12:15",
                  "fine": "14:15"
                },
                {
                  "inizio": "14:15",
                  "fine": "16:15"
                },
                {
                  "inizio": "16:15",
                  "fine": "18:15"
                }
              ]
            },
            {
              "name": "3.0.3",
              "id": 57,
              "occupancy": [
                {
                  "inizio": "08:15",
                  "fine": "10:15"
                },
                {
                  "inizio": "10:15",
                  "fine": "12:15"
                },
                {
                  "inizio": "14:15",
                  "fine": "16:15"
                },
                {
                  "inizio": "18:00",
                  "fine": "20:30"
                }
              ]
            },
            {
              "name": "3.1.1",
              "id": 63,
              "occupancy": [
                {
                  "inizio": "09:15",
                  "fine": "13:15"
                },
                {
                  "inizio": "14:15",
                  "fine": "19:15"
                }
              ]
            },
            {
              "name": "3.1.11",
              "id": 5101,
              "occupancy": [
                {
                  "inizio": "09:15",
                  "fine": "13:15"
                },
                {
                  "inizio": "14:15",
                  "fine": "18:15"
                }
              ]
            },
            {
              "name": "3.1.12",
              "id": 5102,
              "occupancy": [
                {
                  "inizio": "09:15",
                  "fine": "13:15"
                },
                {
                  "inizio": "13:15",
                  "fine": "17:15"
                }
              ]
            },
            {
              "name": "3.1.2",
              "id": 44,
              "occupancy": [
                {
                  "inizio": "08:15",
                  "fine": "11:15"
                },
                {
                  "inizio": "11:15",
                  "fine": "13:15"
                },
                {
                  "inizio": "14:15",
                  "fine": "18:15"
                }
              ]
            },
            {
              "name": "3.1.3",
              "id": 45,
              "occupancy": [
                {
                  "inizio": "09:15",
                  "fine": "11:15"
                },
                {
                  "inizio": "11:15",
                  "fine": "13:15"
                },
                {
                  "inizio": "14:15",
                  "fine": "18:15"
                }
              ]
            },
            {
              "name": "3.1.4",
              "id": 46,
              "occupancy": [
                {
                  "inizio": "08:15",
                  "fine": "10:15"
                },
                {
                  "inizio": "10:15",
                  "fine": "14:15"
                },
                {
                  "inizio": "14:15",
                  "fine": "18:15"
                }
              ]
            },
            {
              "name": "3.1.5",
              "id": 47,
              "occupancy": [
                {
                  "inizio": "08:15",
                  "fine": "10:15"
                },
                {
                  "inizio": "10:15",
                  "fine": "13:15"
                },
                {
                  "inizio": "13:15",
                  "fine": "15:15"
                },
                {
                  "inizio": "15:15",
                  "fine": "17:15"
                }
              ]
            },
            {
              "name": "3.1.6",
              "id": 48,
              "occupancy": [
                {
                  "inizio": "08:15",
                  "fine": "10:15"
                },
                {
                  "inizio": "10:15",
                  "fine": "13:15"
                },
                {
                  "inizio": "15:15",
                  "fine": "17:15"
                }
              ]
            },
            {
              "name": "3.1.7",
              "id": 43,
              "occupancy": [
                {
                  "inizio": "08:15",
                  "fine": "19:15"
                }
              ]
            },
            {
              "name": "3.1.8",
              "id": 4734,
              "occupancy": [
                {
                  "inizio": "08:15",
                  "fine": "10:15"
                },
                {
                  "inizio": "10:15",
                  "fine": "12:15"
                },
                {
                  "inizio": "12:15",
                  "fine": "15:15"
                },
                {
                  "inizio": "15:15",
                  "fine": "17:15"
                }
              ]
            },
            {
              "name": "3.1.9",
              "id": 4733,
              "occupancy": [
                {
                  "inizio": "08:15",
                  "fine": "10:15"
                },
                {
                  "inizio": "10:15",
                  "fine": "12:15"
                },
                {
                  "inizio": "12:15",
                  "fine": "15:15"
                },
                {
                  "inizio": "15:15",
                  "fine": "18:15"
                }
              ]
            },
            {
              "name": "3.2.1",
              "id": 4630,
              "occupancy": [
                {
                  "inizio": "08:15",
                  "fine": "19:15"
                }
              ]
            },
            {
              "name": "3.2.2",
              "id": 4631,
              "occupancy": [
                {
                  "inizio": "08:15",
                  "fine": "19:15"
                }
              ]
            },
            {
              "name": "3.2.3",
              "id": 4632,
              "occupancy": [
                {
                  "inizio": "09:15",
                  "fine": "18:15"
                }
              ]
            },
            {
              "name": "3.2.4",
              "id": 4633,
              "occupancy": [
                {
                  "inizio": "08:15",
                  "fine": "19:15"
                }
              ]
            }
          ]
        },
        {
          "name": "Edificio 4",
          "classrooms": [
            {
              "name": "4.0.1",
              "id": 75,
              "occupancy": [
                {
                  "inizio": "11:15",
                  "fine": "14:15"
                },
                {
                  "inizio": "14:15",
                  "fine": "17:15"
                },
                {
                  "inizio": "18:15",
                  "fine": "21:00"
                }
              ]
            }
          ]
        },
        {
          "name": "Edificio 5",
          "classrooms": [
            {
              "name": "5.0.1",
              "id": 2,
              "occupancy": [
                {
                  "inizio": "08:15",
                  "fine": "11:15"
                },
                {
                  "inizio": "11:15",
                  "fine": "13:15"
                },
                {
                  "inizio": "14:15",
                  "fine": "17:15"
                }
              ]
            },
            {
              "name": "5.0.2",
              "id": 4738,
              "occupancy": [
                {
                  "inizio": "10:15",
                  "fine": "13:15"
                },
                {
                  "inizio": "14:15",
                  "fine": "16:15"
                },
                {
                  "inizio": "16:15",
                  "fine": "18:15"
                }
              ]
            },
            {
              "name": "5.0.3",
              "id": 4739,
              "occupancy": [
                {
                  "inizio": "08:15",
                  "fine": "10:15"
                },
                {
                  "inizio": "10:15",
                  "fine": "12:15"
                },
                {
                  "inizio": "12:15",
                  "fine": "14:15"
                },
                {
                  "inizio": "15:15",
                  "fine": "17:15"
                },
                {
                  "inizio": "18:15",
                  "fine": "20:15"
                }
              ]
            },
            {
              "name": "BELTRAMI",
              "id": 2350,
              "occupancy": [
                {
                  "inizio": "09:00",
                  "fine": "18:30"
                }
              ]
            },
            {
              "name": "5.1.1",
              "id": 3,
              "occupancy": [
                {
                  "inizio": "08:15",
                  "fine": "10:15"
                },
                {
                  "inizio": "10:15",
                  "fine": "13:15"
                },
                {
                  "inizio": "14:15",
                  "fine": "16:15"
                },
                {
                  "inizio": "16:15",
                  "fine": "19:15"
                }
              ]
            }
          ]
        },
        {
          "name": "Edificio 6",
          "classrooms": [
            {
              "name": "6.0.1",
              "id": 10,
              "occupancy": [
                {
                  "inizio": "08:15",
                  "fine": "10:15"
                },
                {
                  "inizio": "10:15",
                  "fine": "12:15"
                },
                {
                  "inizio": "16:15",
                  "fine": "19:15"
                }
              ]
            }
          ]
        },
        {
          "name": "Edificio 7",
          "classrooms": [
            {
              "name": "7.1.1",
              "id": 4,
              "occupancy": [
                {
                  "inizio": "08:15",
                  "fine": "10:15"
                },
                {
                  "inizio": "10:15",
                  "fine": "14:15"
                },
                {
                  "inizio": "15:15",
                  "fine": "17:15"
                }
              ]
            },
            {
              "name": "7.1.2",
              "id": 5,
              "occupancy": [
                {
                  "inizio": "08:15",
                  "fine": "10:15"
                },
                {
                  "inizio": "10:15",
                  "fine": "12:15"
                },
                {
                  "inizio": "13:15",
                  "fine": "16:15"
                }
              ]
            },
            {
              "name": "7.1.3",
              "id": 6,
              "occupancy": [
                {
                  "inizio": "08:15",
                  "fine": "10:15"
                },
                {
                  "inizio": "10:15",
                  "fine": "12:15"
                },
                {
                  "inizio": "14:15",
                  "fine": "16:15"
                },
                {
                  "inizio": "16:15",
                  "fine": "18:15"
                }
              ]
            },
            {
              "name": "7.0.1",
              "id": 4589,
              "occupancy": [
                {
                  "inizio": "08:15",
                  "fine": "10:15"
                },
                {
                  "inizio": "10:15",
                  "fine": "13:15"
                },
                {
                  "inizio": "14:15",
                  "fine": "19:15"
                }
              ]
            }
          ]
        },
        {
          "name": "Edificio 8",
          "classrooms": [
            {
              "name": "8.0.1",
              "id": 27,
              "occupancy": [
                {
                  "inizio": "08:15",
                  "fine": "10:15"
                },
                {
                  "inizio": "10:15",
                  "fine": "12:15"
                },
                {
                  "inizio": "14:15",
                  "fine": "16:15"
                },
                {
                  "inizio": "16:15",
                  "fine": "18:15"
                }
              ]
            },
            {
              "name": "8.1.1",
              "id": 28,
              "occupancy": [
                {
                  "inizio": "08:15",
                  "fine": "12:15"
                },
                {
                  "inizio": "14:15",
                  "fine": "16:15"
                }
              ]
            }
          ]
        },
        {
          "name": "Edificio 9",
          "classrooms": [
            {
              "name": "9.0.1",
              "id": 7,
              "occupancy": [
                {
                  "inizio": "08:15",
                  "fine": "10:15"
                },
                {
                  "inizio": "10:15",
                  "fine": "13:15"
                },
                {
                  "inizio": "15:15",
                  "fine": "17:15"
                }
              ]
            },
            {
              "name": "9.0.2",
              "id": 8,
              "occupancy": [
                {
                  "inizio": "10:15",
                  "fine": "12:15"
                },
                {
                  "inizio": "12:15",
                  "fine": "14:15"
                },
                {
                  "inizio": "14:15",
                  "fine": "18:15"
                }
              ]
            },
            {
              "name": "9.0.3",
              "id": 4740,
              "occupancy": [
                {
                  "inizio": "10:15",
                  "fine": "12:15"
                },
                {
                  "inizio": "12:15",
                  "fine": "15:15"
                },
                {
                  "inizio": "15:15",
                  "fine": "17:15"
                },
                {
                  "inizio": "18:15",
                  "fine": "20:16"
                }
              ]
            },
            {
              "name": "9.0.4",
              "id": 4765,
              "occupancy": [
                {
                  "inizio": "08:00",
                  "fine": "19:15"
                }
              ]
            },
            {
              "name": "9.1.2",
              "id": 9,
              "occupancy": [
                {
                  "inizio": "08:15",
                  "fine": "09:15"
                },
                {
                  "inizio": "09:15",
                  "fine": "11:15"
                },
                {
                  "inizio": "11:15",
                  "fine": "13:15"
                },
                {
                  "inizio": "13:15",
                  "fine": "15:15"
                },
                {
                  "inizio": "15:15",
                  "fine": "17:15"
                }
              ]
            }
          ]
        },
        {
          "name": "Edificio 11",
          "classrooms": [
            {
              "name": "IV",
              "id": 741,
              "occupancy": [
                {
                  "inizio": "12:15",
                  "fine": "14:15"
                },
                {
                  "inizio": "15:15",
                  "fine": "18:15"
                }
              ]
            },
            {
              "name": "A - ALDO ROSSI",
              "id": 721,
              "occupancy": [
                {
                  "inizio": "09:15",
                  "fine": "12:15"
                },
                {
                  "inizio": "13:15",
                  "fine": "16:15"
                },
                {
                  "inizio": "17:45",
                  "fine": "19:30"
                }
              ]
            },
            {
              "name": "B",
              "id": 722,
              "occupancy": [
                {
                  "inizio": "09:15",
                  "fine": "12:15"
                },
                {
                  "inizio": "13:15",
                  "fine": "16:15"
                }
              ]
            },
            {
              "name": "C",
              "id": 723,
              "occupancy": [
                {
                  "inizio": "08:15",
                  "fine": "11:15"
                },
                {
                  "inizio": "14:15",
                  "fine": "18:15"
                }
              ]
            },
            {
              "name": "D",
              "id": 724,
              "occupancy": [
                {
                  "inizio": "09:15",
                  "fine": "11:15"
                },
                {
                  "inizio": "12:15",
                  "fine": "16:15"
                },
                {
                  "inizio": "16:15",
                  "fine": "18:15"
                }
              ]
            },
            {
              "name": "E/F",
              "id": 1941,
              "occupancy": [
                {
                  "inizio": "08:15",
                  "fine": "13:15"
                },
                {
                  "inizio": "15:15",
                  "fine": "17:15"
                }
              ]
            },
            {
              "name": "III.A",
              "id": 732,
              "occupancy": [
                {
                  "inizio": "08:15",
                  "fine": "19:15"
                }
              ]
            },
            {
              "name": "III.B",
              "id": 733,
              "occupancy": [
                {
                  "inizio": "09:15",
                  "fine": "13:15"
                },
                {
                  "inizio": "14:15",
                  "fine": "19:15"
                }
              ]
            },
            {
              "name": "III.C",
              "id": 734,
              "occupancy": [
                {
                  "inizio": "08:15",
                  "fine": "19:15"
                }
              ]
            },
            {
              "name": "III.D",
              "id": 736,
              "occupancy": [
                {
                  "inizio": "09:15",
                  "fine": "13:15"
                },
                {
                  "inizio": "14:15",
                  "fine": "18:15"
                },
                {
                  "inizio": "18:15",
                  "fine": "20:16"
                }
              ]
            },
            {
              "name": "O.1",
              "id": 4684,
              "occupancy": [
                {
                  "inizio": "09:15",
                  "fine": "14:15"
                },
                {
                  "inizio": "14:15",
                  "fine": "18:15"
                },
                {
                  "inizio": "18:15",
                  "fine": "20:45"
                }
              ]
            },
            {
              "name": "Q.1",
              "id": 730,
              "occupancy": [
                {
                  "inizio": "13:15",
                  "fine": "19:15"
                }
              ]
            },
            {
              "name": "R.1",
              "id": 731,
              "occupancy": [
                {
                  "inizio": "09:15",
                  "fine": "13:15"
                },
                {
                  "inizio": "14:15",
                  "fine": "18:15"
                }
              ]
            },
            {
              "name": "U.1",
              "id": 737,
              "occupancy": [
                {
                  "inizio": "09:15",
                  "fine": "17:15"
                }
              ]
            },
            {
              "name": "Y.1",
              "id": 5038,
              "occupancy": [
                {
                  "inizio": "09:15",
                  "fine": "14:15"
                }
              ]
            },
            {
              "name": "Z.1 D.I.",
              "id": 5039,
              "occupancy": [
                {
                  "inizio": "13:15",
                  "fine": "19:15"
                }
              ]
            },
            {
              "name": "J.2",
              "id": 728,
              "occupancy": []
            },
            {
              "name": "O.2",
              "id": 729,
              "occupancy": [
                {
                  "inizio": "08:15",
                  "fine": "19:15"
                }
              ]
            },
            {
              "name": "O.2.1",
              "id": 1942,
              "occupancy": [
                {
                  "inizio": "08:15",
                  "fine": "19:15"
                }
              ]
            },
            {
              "name": "R.2",
              "id": 4682,
              "occupancy": [
                {
                  "inizio": "09:15",
                  "fine": "17:15"
                }
              ]
            },
            {
              "name": "U.2",
              "id": 738,
              "occupancy": [
                {
                  "inizio": "09:15",
                  "fine": "14:15"
                }
              ]
            },
            {
              "name": "Z.2",
              "id": 1960,
              "occupancy": [
                {
                  "inizio": "08:15",
                  "fine": "19:15"
                }
              ]
            },
            {
              "name": "G.1",
              "id": 726,
              "occupancy": [
                {
                  "inizio": "11:15",
                  "fine": "13:15"
                },
                {
                  "inizio": "14:15",
                  "fine": "16:15"
                }
              ]
            },
            {
              "name": "G.2",
              "id": 2012,
              "occupancy": [
                {
                  "inizio": "09:15",
                  "fine": "17:15"
                }
              ]
            },
            {
              "name": "G.3",
              "id": 4791,
              "occupancy": [
                {
                  "inizio": "10:15",
                  "fine": "12:15"
                }
              ]
            }
          ]
        },
        {
          "name": "Edificio 13 (Trifoglio)",
          "classrooms": [
            {
              "name": "T.1.1",
              "id": 53,
              "occupancy": [
                {
                  "inizio": "10:15",
                  "fine": "13:15"
                },
                {
                  "inizio": "14:15",
                  "fine": "16:15"
                },
                {
                  "inizio": "16:15",
                  "fine": "18:15"
                }
              ]
            },
            {
              "name": "T.1.2",
              "id": 71,
              "occupancy": [
                {
                  "inizio": "10:15",
                  "fine": "13:15"
                },
                {
                  "inizio": "15:15",
                  "fine": "19:15"
                }
              ]
            },
            {
              "name": "T.1.3",
              "id": 72,
              "occupancy": [
                {
                  "inizio": "08:15",
                  "fine": "11:15"
                },
                {
                  "inizio": "11:15",
                  "fine": "14:15"
                },
                {
                  "inizio": "14:15",
                  "fine": "17:15"
                }
              ]
            },
            {
              "name": "T.2.1",
              "id": 54,
              "occupancy": [
                {
                  "inizio": "08:15",
                  "fine": "10:15"
                },
                {
                  "inizio": "10:15",
                  "fine": "12:15"
                },
                {
                  "inizio": "15:15",
                  "fine": "17:15"
                }
              ]
            },
            {
              "name": "T.2.2",
              "id": 55,
              "occupancy": [
                {
                  "inizio": "08:15",
                  "fine": "10:15"
                },
                {
                  "inizio": "10:15",
                  "fine": "13:15"
                },
                {
                  "inizio": "13:15",
                  "fine": "15:15"
                },
                {
                  "inizio": "15:15",
                  "fine": "17:15"
                }
              ]
            },
            {
              "name": "T.2.3",
              "id": 56,
              "occupancy": [
                {
                  "inizio": "08:15",
                  "fine": "10:15"
                },
                {
                  "inizio": "10:15",
                  "fine": "13:15"
                }
              ]
            },
            {
              "name": "T.0.1",
              "id": 65,
              "occupancy": [
                {
                  "inizio": "09:15",
                  "fine": "11:15"
                },
                {
                  "inizio": "11:15",
                  "fine": "13:15"
                },
                {
                  "inizio": "14:15",
                  "fine": "16:15"
                },
                {
                  "inizio": "16:15",
                  "fine": "18:15"
                }
              ]
            },
            {
              "name": "T.0.2",
              "id": 52,
              "occupancy": [
                {
                  "inizio": "08:15",
                  "fine": "10:15"
                },
                {
                  "inizio": "10:15",
                  "fine": "12:15"
                },
                {
                  "inizio": "12:15",
                  "fine": "14:15"
                },
                {
                  "inizio": "14:15",
                  "fine": "16:15"
                },
                {
                  "inizio": "16:15",
                  "fine": "18:15"
                }
              ]
            },
            {
              "name": "T.0.3",
              "id": 1081,
              "occupancy": [
                {
                  "inizio": "08:15",
                  "fine": "13:15"
                },
                {
                  "inizio": "14:15",
                  "fine": "18:15"
                }
              ]
            },
            {
              "name": "T.0.4",
              "id": 261,
              "occupancy": [
                {
                  "inizio": "08:15",
                  "fine": "10:15"
                },
                {
                  "inizio": "10:15",
                  "fine": "12:15"
                },
                {
                  "inizio": "12:15",
                  "fine": "14:15"
                },
                {
                  "inizio": "15:15",
                  "fine": "17:15"
                },
                {
                  "inizio": "17:15",
                  "fine": "20:15"
                }
              ]
            }
          ]
        },
        {
          "name": "Edificio 14 (Nave)",
          "classrooms": [
            {
              "name": "B.2.1",
              "id": 20,
              "occupancy": [
                {
                  "inizio": "08:15",
                  "fine": "19:15"
                }
              ]
            },
            {
              "name": "B.2.2",
              "id": 31,
              "occupancy": [
                {
                  "inizio": "10:15",
                  "fine": "12:15"
                },
                {
                  "inizio": "14:15",
                  "fine": "18:15"
                }
              ]
            },
            {
              "name": "B.2.3",
              "id": 2000,
              "occupancy": [
                {
                  "inizio": "08:15",
                  "fine": "10:15"
                },
                {
                  "inizio": "10:15",
                  "fine": "12:15"
                },
                {
                  "inizio": "14:15",
                  "fine": "18:15"
                }
              ]
            },
            {
              "name": "B.2.4",
              "id": 2001,
              "occupancy": [
                {
                  "inizio": "08:15",
                  "fine": "10:15"
                },
                {
                  "inizio": "10:15",
                  "fine": "12:15"
                },
                {
                  "inizio": "12:15",
                  "fine": "14:15"
                },
                {
                  "inizio": "14:15",
                  "fine": "16:15"
                },
                {
                  "inizio": "16:15",
                  "fine": "18:15"
                }
              ]
            },
            {
              "name": "B.3.1",
              "id": 73,
              "occupancy": [
                {
                  "inizio": "09:15",
                  "fine": "13:15"
                },
                {
                  "inizio": "14:15",
                  "fine": "16:15"
                },
                {
                  "inizio": "16:15",
                  "fine": "18:15"
                }
              ]
            },
            {
              "name": "B.3.2",
              "id": 74,
              "occupancy": [
                {
                  "inizio": "09:15",
                  "fine": "13:15"
                },
                {
                  "inizio": "14:15",
                  "fine": "18:15"
                }
              ]
            },
            {
              "name": "B.3.3",
              "id": 2002,
              "occupancy": [
                {
                  "inizio": "09:15",
                  "fine": "13:15"
                },
                {
                  "inizio": "14:15",
                  "fine": "16:15"
                }
              ]
            },
            {
              "name": "B.3.4",
              "id": 2003,
              "occupancy": [
                {
                  "inizio": "08:15",
                  "fine": "10:15"
                },
                {
                  "inizio": "10:15",
                  "fine": "12:15"
                },
                {
                  "inizio": "13:15",
                  "fine": "15:15"
                },
                {
                  "inizio": "15:15",
                  "fine": "17:15"
                }
              ]
            },
            {
              "name": "B.4.1",
              "id": 101,
              "occupancy": [
                {
                  "inizio": "09:15",
                  "fine": "13:15"
                },
                {
                  "inizio": "14:15",
                  "fine": "18:15"
                }
              ]
            },
            {
              "name": "B.4.2",
              "id": 1226,
              "occupancy": [
                {
                  "inizio": "09:15",
                  "fine": "14:15"
                },
                {
                  "inizio": "14:15",
                  "fine": "18:15"
                }
              ]
            },
            {
              "name": "B.4.3",
              "id": 4590,
              "occupancy": [
                {
                  "inizio": "09:15",
                  "fine": "13:15"
                },
                {
                  "inizio": "14:15",
                  "fine": "18:15"
                }
              ]
            },
            {
              "name": "B.4.4",
              "id": 4725,
              "occupancy": [
                {
                  "inizio": "08:15",
                  "fine": "10:15"
                },
                {
                  "inizio": "10:15",
                  "fine": "13:15"
                },
                {
                  "inizio": "13:15",
                  "fine": "15:15"
                },
                {
                  "inizio": "15:15",
                  "fine": "17:15"
                }
              ]
            },
            {
              "name": "B.5.1",
              "id": 1221,
              "occupancy": [
                {
                  "inizio": "08:15",
                  "fine": "11:15"
                },
                {
                  "inizio": "11:15",
                  "fine": "13:15"
                },
                {
                  "inizio": "14:15",
                  "fine": "16:15"
                },
                {
                  "inizio": "16:15",
                  "fine": "18:15"
                }
              ]
            },
            {
              "name": "B.5.2",
              "id": 1222,
              "occupancy": [
                {
                  "inizio": "08:15",
                  "fine": "11:15"
                },
                {
                  "inizio": "11:15",
                  "fine": "14:15"
                },
                {
                  "inizio": "16:15",
                  "fine": "18:15"
                }
              ]
            },
            {
              "name": "B.5.3",
              "id": 1223,
              "occupancy": [
                {
                  "inizio": "08:15",
                  "fine": "10:15"
                },
                {
                  "inizio": "10:15",
                  "fine": "12:15"
                },
                {
                  "inizio": "12:15",
                  "fine": "14:15"
                },
                {
                  "inizio": "14:15",
                  "fine": "17:15"
                }
              ]
            },
            {
              "name": "B.5.4",
              "id": 1224,
              "occupancy": [
                {
                  "inizio": "08:15",
                  "fine": "10:15"
                },
                {
                  "inizio": "10:15",
                  "fine": "13:15"
                },
                {
                  "inizio": "15:15",
                  "fine": "17:15"
                }
              ]
            },
            {
              "name": "B.6.1",
              "id": 962,
              "occupancy": [
                {
                  "inizio": "08:15",
                  "fine": "10:15"
                },
                {
                  "inizio": "10:15",
                  "fine": "12:15"
                },
                {
                  "inizio": "13:15",
                  "fine": "15:15"
                },
                {
                  "inizio": "15:15",
                  "fine": "17:15"
                }
              ]
            },
            {
              "name": "B.6.2",
              "id": 964,
              "occupancy": [
                {
                  "inizio": "08:15",
                  "fine": "19:15"
                }
              ]
            },
            {
              "name": "B.6.3",
              "id": 965,
              "occupancy": [
                {
                  "inizio": "08:15",
                  "fine": "19:15"
                }
              ]
            },
            {
              "name": "B.6.4",
              "id": 1225,
              "occupancy": [
                {
                  "inizio": "08:15",
                  "fine": "13:15"
                },
                {
                  "inizio": "14:15",
                  "fine": "16:15"
                }
              ]
            }
          ]
        },
        {
          "name": "Edificio 16B",
          "classrooms": [
            {
              "name": "16B.1.1",
              "id": 4991,
              "occupancy": [
                {
                  "inizio": "10:15",
                  "fine": "12:15"
                },
                {
                  "inizio": "14:15",
                  "fine": "19:15"
                }
              ]
            },
            {
              "name": "16B.2.1",
              "id": 4992,
              "occupancy": [
                {
                  "inizio": "09:15",
                  "fine": "13:15"
                },
                {
                  "inizio": "15:15",
                  "fine": "18:15"
                }
              ]
            },
            {
              "name": "16B.3.1",
              "id": 4993,
              "occupancy": [
                {
                  "inizio": "09:15",
                  "fine": "12:15"
                },
                {
                  "inizio": "15:15",
                  "fine": "18:15"
                }
              ]
            },
            {
              "name": "16B.0.1",
              "id": 4990,
              "occupancy": [
                {
                  "inizio": "09:15",
                  "fine": "13:15"
                },
                {
                  "inizio": "14:15",
                  "fine": "18:15"
                }
              ]
            }
          ]
        },
        {
          "name": "Edificio 16C",
          "classrooms": [
            {
              "name": "16C.0.1",
              "id": 5011,
              "occupancy": [
                {
                  "inizio": "08:15",
                  "fine": "19:15"
                }
              ]
            },
            {
              "name": "16C.0.2",
              "id": 5012,
              "occupancy": [
                {
                  "inizio": "08:15",
                  "fine": "19:15"
                }
              ]
            },
            {
              "name": "16C.0.3",
              "id": 5013,
              "occupancy": [
                {
                  "inizio": "08:15",
                  "fine": "19:15"
                }
              ]
            }
          ]
        },
        {
          "name": "Edificio 19",
          "classrooms": [
            {
              "name": "19.0.1",
              "id": 161,
              "occupancy": [
                {
                  "inizio": "09:15",
                  "fine": "10:15"
                },
                {
                  "inizio": "10:15",
                  "fine": "13:15"
                },
                {
                  "inizio": "13:15",
                  "fine": "15:15"
                },
                {
                  "inizio": "15:15",
                  "fine": "17:15"
                }
              ]
            }
          ]
        },
        {
          "name": "Edificio 20",
          "classrooms": [
            {
              "name": "20.S.1",
              "id": 282,
              "occupancy": [
                {
                  "inizio": "10:15",
                  "fine": "13:15"
                },
                {
                  "inizio": "13:15",
                  "fine": "15:15"
                },
                {
                  "inizio": "15:15",
                  "fine": "18:15"
                }
              ]
            }
          ]
        },
        {
          "name": "Edificio 21",
          "classrooms": [
            {
              "name": "21.0.1",
              "id": 67,
              "occupancy": [
                {
                  "inizio": "10:15",
                  "fine": "12:15"
                },
                {
                  "inizio": "13:15",
                  "fine": "15:15"
                },
                {
                  "inizio": "15:15",
                  "fine": "17:15"
                }
              ]
            },
            {
              "name": "21.0.2",
              "id": 1541,
              "occupancy": []
            },
            {
              "name": "21.0.3",
              "id": 25,
              "occupancy": [
                {
                  "inizio": "08:15",
                  "fine": "10:15"
                },
                {
                  "inizio": "10:15",
                  "fine": "13:15"
                },
                {
                  "inizio": "15:15",
                  "fine": "17:15"
                }
              ]
            },
            {
              "name": "21.S.1",
              "id": 21,
              "occupancy": [
                {
                  "inizio": "08:15",
                  "fine": "10:15"
                },
                {
                  "inizio": "10:15",
                  "fine": "12:15"
                },
                {
                  "inizio": "12:15",
                  "fine": "14:15"
                },
                {
                  "inizio": "14:15",
                  "fine": "17:15"
                }
              ]
            },
            {
              "name": "21.S.2",
              "id": 19,
              "occupancy": [
                {
                  "inizio": "08:15",
                  "fine": "10:15"
                },
                {
                  "inizio": "10:15",
                  "fine": "13:15"
                },
                {
                  "inizio": "15:15",
                  "fine": "17:15"
                }
              ]
            },
            {
              "name": "21.S.3",
              "id": 22,
              "occupancy": [
                {
                  "inizio": "08:15",
                  "fine": "10:15"
                },
                {
                  "inizio": "11:15",
                  "fine": "13:15"
                },
                {
                  "inizio": "15:15",
                  "fine": "17:15"
                }
              ]
            },
            {
              "name": "21.S.4",
              "id": 23,
              "occupancy": [
                {
                  "inizio": "08:15",
                  "fine": "12:15"
                },
                {
                  "inizio": "15:15",
                  "fine": "17:15"
                }
              ]
            }
          ]
        },
        {
          "name": "Edificio 23",
          "classrooms": [
            {
              "name": "G.0.1",
              "id": 1661,
              "occupancy": [
                {
                  "inizio": "08:15",
                  "fine": "12:15"
                }
              ]
            },
            {
              "name": "G.0.2",
              "id": 1662,
              "occupancy": [
                {
                  "inizio": "08:15",
                  "fine": "12:15"
                }
              ]
            }
          ]
        },
        {
          "name": "Edificio 25",
          "classrooms": [
            {
              "name": "25.0.1",
              "id": 945,
              "occupancy": [
                {
                  "inizio": "08:15",
                  "fine": "10:15"
                },
                {
                  "inizio": "10:15",
                  "fine": "12:15"
                },
                {
                  "inizio": "14:15",
                  "fine": "17:15"
                }
              ]
            },
            {
              "name": "25.0.2",
              "id": 946,
              "occupancy": [
                {
                  "inizio": "08:15",
                  "fine": "11:15"
                },
                {
                  "inizio": "13:15",
                  "fine": "15:15"
                },
                {
                  "inizio": "15:15",
                  "fine": "17:15"
                }
              ]
            },
            {
              "name": "25.1.1",
              "id": 947,
              "occupancy": [
                {
                  "inizio": "08:15",
                  "fine": "10:15"
                },
                {
                  "inizio": "10:15",
                  "fine": "13:15"
                },
                {
                  "inizio": "13:15",
                  "fine": "15:15"
                },
                {
                  "inizio": "15:15",
                  "fine": "18:15"
                }
              ]
            },
            {
              "name": "25.1.2",
              "id": 948,
              "occupancy": [
                {
                  "inizio": "08:15",
                  "fine": "10:15"
                },
                {
                  "inizio": "10:15",
                  "fine": "12:15"
                },
                {
                  "inizio": "12:15",
                  "fine": "14:15"
                },
                {
                  "inizio": "14:15",
                  "fine": "16:15"
                },
                {
                  "inizio": "16:15",
                  "fine": "18:15"
                }
              ]
            },
            {
              "name": "25.1.3",
              "id": 949,
              "occupancy": [
                {
                  "inizio": "08:15",
                  "fine": "10:15"
                },
                {
                  "inizio": "10:15",
                  "fine": "13:15"
                },
                {
                  "inizio": "16:15",
                  "fine": "19:15"
                }
              ]
            },
            {
              "name": "25.1.4",
              "id": 950,
              "occupancy": [
                {
                  "inizio": "08:15",
                  "fine": "10:15"
                },
                {
                  "inizio": "10:15",
                  "fine": "12:15"
                },
                {
                  "inizio": "12:15",
                  "fine": "15:15"
                }
              ]
            },
            {
              "name": "25.1.5",
              "id": 951,
              "occupancy": [
                {
                  "inizio": "08:15",
                  "fine": "11:15"
                },
                {
                  "inizio": "11:15",
                  "fine": "13:15"
                },
                {
                  "inizio": "13:15",
                  "fine": "15:15"
                },
                {
                  "inizio": "15:15",
                  "fine": "17:15"
                },
                {
                  "inizio": "17:15",
                  "fine": "19:15"
                }
              ]
            },
            {
              "name": "25.1.6",
              "id": 952,
              "occupancy": [
                {
                  "inizio": "08:15",
                  "fine": "10:15"
                },
                {
                  "inizio": "10:15",
                  "fine": "12:15"
                },
                {
                  "inizio": "13:15",
                  "fine": "15:15"
                },
                {
                  "inizio": "15:15",
                  "fine": "17:15"
                }
              ]
            },
            {
              "name": "25.2.1",
              "id": 1305,
              "occupancy": [
                {
                  "inizio": "08:15",
                  "fine": "10:15"
                },
                {
                  "inizio": "10:15",
                  "fine": "12:15"
                },
                {
                  "inizio": "12:15",
                  "fine": "14:15"
                },
                {
                  "inizio": "14:15",
                  "fine": "16:15"
                }
              ]
            },
            {
              "name": "25.2.2",
              "id": 1306,
              "occupancy": [
                {
                  "inizio": "08:15",
                  "fine": "10:15"
                },
                {
                  "inizio": "13:15",
                  "fine": "15:15"
                },
                {
                  "inizio": "15:15",
                  "fine": "17:15"
                }
              ]
            },
            {
              "name": "25.2.3",
              "id": 1307,
              "occupancy": [
                {
                  "inizio": "14:15",
                  "fine": "17:15"
                }
              ]
            },
            {
              "name": "25.S.1",
              "id": 941,
              "occupancy": [
                {
                  "inizio": "08:15",
                  "fine": "10:15"
                },
                {
                  "inizio": "13:15",
                  "fine": "15:15"
                },
                {
                  "inizio": "15:15",
                  "fine": "17:15"
                }
              ]
            },
            {
              "name": "25.S.2",
              "id": 942,
              "occupancy": []
            },
            {
              "name": "25.S.3",
              "id": 944,
              "occupancy": [
                {
                  "inizio": "09:00",
                  "fine": "18:30"
                }
              ]
            }
          ]
        },
        {
          "name": "Edificio 26",
          "classrooms": [
            {
              "name": "26.0.1",
              "id": 4666,
              "occupancy": [
                {
                  "inizio": "08:15",
                  "fine": "10:15"
                },
                {
                  "inizio": "10:15",
                  "fine": "12:15"
                },
                {
                  "inizio": "12:15",
                  "fine": "14:15"
                },
                {
                  "inizio": "14:15",
                  "fine": "17:15"
                },
                {
                  "inizio": "17:15",
                  "fine": "19:15"
                }
              ]
            },
            {
              "name": "26.0.2",
              "id": 4599,
              "occupancy": [
                {
                  "inizio": "08:15",
                  "fine": "10:15"
                },
                {
                  "inizio": "10:15",
                  "fine": "12:15"
                },
                {
                  "inizio": "14:15",
                  "fine": "17:15"
                }
              ]
            },
            {
              "name": "26.0.3",
              "id": 4600,
              "occupancy": [
                {
                  "inizio": "12:15",
                  "fine": "16:15"
                },
                {
                  "inizio": "16:15",
                  "fine": "19:15"
                }
              ]
            },
            {
              "name": "26.0.4",
              "id": 4628,
              "occupancy": [
                {
                  "inizio": "15:15",
                  "fine": "18:15"
                }
              ]
            },
            {
              "name": "26.1.1",
              "id": 4601,
              "occupancy": [
                {
                  "inizio": "08:15",
                  "fine": "10:15"
                },
                {
                  "inizio": "10:15",
                  "fine": "13:15"
                },
                {
                  "inizio": "13:15",
                  "fine": "15:15"
                },
                {
                  "inizio": "15:15",
                  "fine": "17:15"
                }
              ]
            },
            {
              "name": "26.1.2",
              "id": 4602,
              "occupancy": [
                {
                  "inizio": "08:15",
                  "fine": "13:15"
                },
                {
                  "inizio": "15:15",
                  "fine": "18:15"
                }
              ]
            },
            {
              "name": "26.1.3",
              "id": 4603,
              "occupancy": [
                {
                  "inizio": "13:15",
                  "fine": "15:15"
                },
                {
                  "inizio": "15:15",
                  "fine": "17:15"
                }
              ]
            },
            {
              "name": "26.1.4",
              "id": 4604,
              "occupancy": [
                {
                  "inizio": "08:15",
                  "fine": "11:15"
                },
                {
                  "inizio": "11:15",
                  "fine": "14:15"
                },
                {
                  "inizio": "14:15",
                  "fine": "16:15"
                }
              ]
            },
            {
              "name": "26.1.5",
              "id": 4605,
              "occupancy": [
                {
                  "inizio": "08:15",
                  "fine": "10:15"
                },
                {
                  "inizio": "10:15",
                  "fine": "12:15"
                },
                {
                  "inizio": "13:15",
                  "fine": "15:15"
                },
                {
                  "inizio": "15:15",
                  "fine": "18:15"
                }
              ]
            },
            {
              "name": "16.1.6",
              "id": 4606,
              "occupancy": [
                {
                  "inizio": "08:15",
                  "fine": "10:15"
                },
                {
                  "inizio": "10:15",
                  "fine": "13:15"
                },
                {
                  "inizio": "14:15",
                  "fine": "18:15"
                }
              ]
            }
          ]
        }
      ]
    },
    {
      "name": "SEDE VIA COLOMBO 40",
      "id": "MIA06",
      "buildings": [
        {
          "name": "Edificio 32.1",
          "classrooms": [
            {
              "name": "E.P.6",
              "id": 5098,
              "occupancy": [
                {
                  "inizio": "08:15",
                  "fine": "10:15"
                },
                {
                  "inizio": "10:15",
                  "fine": "13:15"
                },
                {
                  "inizio": "15:15",
                  "fine": "18:15"
                }
              ]
            },
            {
              "name": "E.P.7",
              "id": 5099,
              "occupancy": [
                {
                  "inizio": "09:15",
                  "fine": "13:15"
                },
                {
                  "inizio": "13:15",
                  "fine": "16:15"
                }
              ]
            }
          ]
        },
        {
          "name": "Edificio 32.3",
          "classrooms": [
            {
              "name": "E.P.1",
              "id": 4596,
              "occupancy": [
                {
                  "inizio": "11:15",
                  "fine": "18:15"
                }
              ]
            },
            {
              "name": "E.P.2",
              "id": 4752,
              "occupancy": [
                {
                  "inizio": "14:15",
                  "fine": "18:15"
                }
              ]
            },
            {
              "name": "E.P.3",
              "id": 4766,
              "occupancy": []
            }
          ]
        }
      ]
    },
    {
      "name": "SEDE BOVISA - Via Durando",
      "id": "MIB02",
      "buildings": []
    },
    {
      "name": "SEDE BOVISA - Via La Masa",
      "id": "MIB01",
      "buildings": []
    },
    {
      "name": "SEDE CREMONA - Via Bissolati",
      "id": "CRG02",
      "buildings": []
    },
    {
      "name": "SEDE CREMONA - Via Pontevico",
      "id": "CRG01",
      "buildings": []
    },
    {
      "name": "SEDE LECCO",
      "id": "LCF04",
      "buildings": []
    },
    {
      "name": "SEDE MANTOVA",
      "id": "MNG01",
      "buildings": []
    }
  ]
}